pyjoycon/__init__.py
pyjoycon/constants.py
pyjoycon/device.py
pyjoycon/event.py
pyjoycon/gyro.py
pyjoycon/joycon.py
pyjoycon/wrappers.py
joycon_python-0.2.4.dist-info/LICENSE
joycon_python-0.2.4.dist-info/METADATA
joycon_python-0.2.4.dist-info/WHEEL
joycon_python-0.2.4.dist-info/top_level.txt
joycon_python-0.2.4.dist-info/RECORD
