Metadata-Version: 2.1
Name: joycon-python
Version: 0.2.4
Summary: Python driver for Nintendo Switch Joy-Con
Home-page: https://github.com/tokoroten-lab/joycon-python
Author: tokoroten-lab, atsukoba, pbsds
Author-email: tokoroten.lab@gmail.com, atsuya_kobayashi@yahoo.co.jp, pbsds@hotmail.com
License: UNKNOWN
Platform: UNKNOWN
Classifier: Programming Language :: Python :: 3.7
